README.md
s3_unique_bucket.py
setup.py
s3_unique_bucket.egg-info/PKG-INFO
s3_unique_bucket.egg-info/SOURCES.txt
s3_unique_bucket.egg-info/dependency_links.txt
s3_unique_bucket.egg-info/entry_points.txt
s3_unique_bucket.egg-info/requires.txt
s3_unique_bucket.egg-info/top_level.txt