Metadata-Version: 2.1
Name: s3-unique-bucket
Version: 0.1.0
Summary: Insures a unique S3 bucket exists for the account
Home-page: https://github.com/DrLuke/s3-unique-bucket
Author: Lukas Jackowski
License: UNKNOWN
Keywords: aws s3 bucket unique ci cd
Platform: UNKNOWN
Classifier: Development Status :: 4 - Beta
Classifier: Intended Audience :: Developers
Classifier: Topic :: Software Development :: Build Tools
Classifier: License :: OSI Approved :: MIT License
Classifier: Programming Language :: Python :: 3.6
Classifier: Programming Language :: Python :: 3.7
Requires-Python: >=3.6, <4
